juham_simulation/__init__.py
juham_simulation/motionsim.py
juham_simulation/powermetersim.py
juham_simulation/py.typed
juham_simulation/simulation_plugin.py
juham_simulation/temperaturesim.py
juham_simulation/watermetersim.py
juham_simulation-0.1.3.dist-info/licenses/LICENSE.rst
juham_simulation-0.1.3.dist-info/METADATA
juham_simulation-0.1.3.dist-info/WHEEL
juham_simulation-0.1.3.dist-info/entry_points.txt
juham_simulation-0.1.3.dist-info/top_level.txt
juham_simulation-0.1.3.dist-info/RECORD
