Metadata-Version: 2.4
Name: juham-simulation
Version: 0.1.3
Summary: Simulation plugin for Juham
Author-email: J Meskanen <juham.api@gmail.com>
Maintainer-email: "J. Meskanen" <juham.api@gmail.com>
License-Expression: MIT
Project-URL: Homepage, https://gitlab.com/juham/juham/juham-simulation
Project-URL: Bug Reports, https://gitlab.com/juham/juham/juham-simulation
Project-URL: Funding, https://meskanen.com
Project-URL: Say Thanks!, http://meskanen.com
Project-URL: Source, https://gitlab.com/juham/juham/juham-simulation
Keywords: juham,masterpiece,plugin,framework,simulation,home automation
Classifier: Development Status :: 4 - Beta
Classifier: Intended Audience :: Developers
Classifier: Topic :: Software Development
Classifier: Programming Language :: Python :: 3.8
Requires-Python: >=3.8
License-File: LICENSE.rst
Requires-Dist: juham-core>=0.2.6
Requires-Dist: importlib-metadata
Provides-Extra: dev
Requires-Dist: check-manifest; extra == "dev"
Requires-Dist: coverage>=7.0; extra == "dev"
Dynamic: license-file
